{"user1": {"username": "Darshana", "password": "2003", "classes": {"Select": "link", "My": "https://us04web.zoom.us/j/8193572899?pwd=WDJiL1BodmhNa0lCOHNFRTZpbFZyUT09", "ET": "", "SFT": "", "ICT": "https://zoom.us/j/94115234358?pwd=amE0WmVvTGY3WDZBeXBCbG5lTm50UT09", "English": "https://us05web.zoom.us/j/83035297436?pwd=SjEwb3NENUVoRmZ6SzNWY2F4TGlXUT09"}}, "user2": {"username": "Dilshan", "password": "2008", "classes": {"Select": "link", "My": "https://us05web.zoom.us/j/5683040098?pwd=d1FIRnlJZ3ZKb0pVRlV0SWozdDFvQT09"}}, "user3": {"username": "Danuja", "password": "2012", "classes": {"Select": "link"}}, "user4": {"username": "darshana494", "password": "1234", "classes": {"Select": "link", "ET": "ET", "SFT": "SFT", "ICT": "ICT"}}}